eaiscenarioreporter-0.4.10.data/data/assets/valid.png
eaiscenarioreporter-0.4.10.data/data/assets/warning.png
featurereporter/__init__.py
featurereporter/__main__.py
featurereporter/csvformatter.py
featurereporter/desktopApp.py
featurereporter/featurereporter.py
featurereporter/reportgenerator.py
featurereporter/assets/COPYING
featurereporter/assets/LICENSE.txt
featurereporter/assets/plantuml.jar
featurereporter/assets/valid.png
featurereporter/assets/warning.png
eaiscenarioreporter-0.4.10.dist-info/LICENSE.txt
eaiscenarioreporter-0.4.10.dist-info/METADATA
eaiscenarioreporter-0.4.10.dist-info/WHEEL
eaiscenarioreporter-0.4.10.dist-info/entry_points.txt
eaiscenarioreporter-0.4.10.dist-info/top_level.txt
eaiscenarioreporter-0.4.10.dist-info/RECORD
