Metadata-Version: 2.1
Name: eaiscenarioreporter
Version: 0.4.10
Summary: Turns folder of gherkin feature files into a docx file.
Home-page: https://github.com/Hidden-goblin/eaiscenarioreporter.git
Author: Eric Aïvayan
Author-email: eric.aivayan@free.fr
Keywords: BDD,Gherkin,behave,docx
Classifier: Development Status :: 4 - Beta
Classifier: Intended Audience :: Developers
Classifier: License :: OSI Approved :: GNU General Public License v3 (GPLv3)
Classifier: Programming Language :: Python :: 3.7
Classifier: Programming Language :: Python :: 3.8
Classifier: Topic :: Software Development :: Quality Assurance
Classifier: Topic :: Text Processing
Requires-Python: >=3.7, !=2.*
License-File: LICENSE.txt
Requires-Dist: behave
Requires-Dist: python-docx
Requires-Dist: Pillow
Requires-Dist: matplotlib
Requires-Dist: markdown-it-py
Requires-Dist: htmldocx
